{
  "$schema": "http://schema.management.azure.com/schemas/2015-05-01/deploymentParameters.json#",
  "contentVersion": "1.0.0.0",
  "parameters": {
    "newStorageAccountName": {
      "value": "testps01"
    },
    "adminUsername": {
      "value": "azureuser"
    },
    "adminPassword": {
      "value": "Pass123!"
    },
    "mySQLPassword": {
      "value": "MySQL123!"
    },
    "dnsNameForPublicIP": {
      "value": "testps01"
    },
    "adminFirstName": {
      "value": "Thomas"
    },
    "adminLastName": {
      "value": "Conte"
    },
    "adminEmail": {
      "value": "thomas@conte.com"
    },
    "adminPSPassword": {
      "value": "Presta123!"
    }
  }
}
